cmdbase_utils/__init__.py
cmdbase_utils/__main__.py
cmdbase_utils/_version.py
cmdbase_utils/apiclient.py
cmdbase_utils/bases.py
cmdbase_utils/choices.py
cmdbase_utils/conversions.py
cmdbase_utils/settings.py
cmdbase_utils/commands/__init__.py
cmdbase_utils/commands/report.py
cmdbase_utils-0.0.1a2.dist-info/METADATA
cmdbase_utils-0.0.1a2.dist-info/WHEEL
cmdbase_utils-0.0.1a2.dist-info/entry_points.txt
cmdbase_utils-0.0.1a2.dist-info/top_level.txt
cmdbase_utils-0.0.1a2.dist-info/RECORD
