Metadata-Version: 2.1
Name: cmdbase-utils
Version: 0.0.1a2
Summary: Shared utilities for CMDBase and command-line tool interacting with the REST API.
Author-email: Ipamo <dev@ipamo.net>
Project-URL: Homepage, https://gitlab.com/ipamo/cmdbase
Project-URL: Bug Tracker, https://gitlab.com/ipamo/cmdbase/issues
Keywords: cmdb
Classifier: Development Status :: 1 - Planning
Classifier: License :: OSI Approved :: MIT License
Classifier: Operating System :: OS Independent
Classifier: Programming Language :: Python :: 3.11
Requires-Python: >=3.11.2
Requires-Dist: zut >=0.7.8
Requires-Dist: tabulate
Requires-Dist: json-with-comments
